customtransformers/__init__.py
customtransformers/estimators.py
customtransformers/transformers.py
customtransformers/utils_transformers.py
customtransformers-0.1.12.dist-info/METADATA
customtransformers-0.1.12.dist-info/WHEEL
customtransformers-0.1.12.dist-info/top_level.txt
customtransformers-0.1.12.dist-info/RECORD
